LICENSE
MANIFEST.in
README.md
VERSION
pyproject.toml
requirements.txt
setup.py
covalent_oci_plugin/__init__.py
covalent_oci_plugin/oci.py
covalent_oci_plugin.egg-info/PKG-INFO
covalent_oci_plugin.egg-info/SOURCES.txt
covalent_oci_plugin.egg-info/dependency_links.txt
covalent_oci_plugin.egg-info/entry_points.txt
covalent_oci_plugin.egg-info/requires.txt
covalent_oci_plugin.egg-info/top_level.txt
covalent_oci_plugin/assets/infra/.gitignore
covalent_oci_plugin/assets/infra/main.tf
covalent_oci_plugin/assets/infra/oci.conf.tftpl
covalent_oci_plugin/assets/infra/outputs.tf
covalent_oci_plugin/assets/infra/variables.tf
covalent_oci_plugin/assets/infra/versions.tf
covalent_oci_plugin/util/__init__.py
covalent_oci_plugin/util/httpx_auth.py
covalent_oci_plugin/util/httpx_client.py
covalent_oci_plugin/util/misc.py
covalent_oci_plugin/util/user_data.py