Metadata-Version: 2.1
Name: covalent-oci-plugin
Version: 0.3.0
Summary: Covalent OCI Plugin
Home-page: https://github.com/AgnostiqHQ/covalent-oci-plugin
Author: Agnostiq
Author-email: support@agnostiq.ai
Maintainer: Agnostiq
License: Apache License 2.0
Download-URL: https://github.com/AgnostiqHQ/covalent-oci-plugin/archive/v0.3.0.tar.gz
Platform: UNKNOWN
Classifier: Development Status :: 3 - Alpha
Classifier: Environment :: Console
Classifier: Environment :: Plugins
Classifier: Intended Audience :: Developers
Classifier: Intended Audience :: Education
Classifier: Intended Audience :: Science/Research
Classifier: License :: OSI Approved :: Apache Software License
Classifier: Natural Language :: English
Classifier: Operating System :: MacOS
Classifier: Operating System :: POSIX :: Linux
Classifier: Programming Language :: Python :: 3
Classifier: Programming Language :: Python :: 3 :: Only
Classifier: Programming Language :: Python :: 3.8
Classifier: Programming Language :: Python :: 3.9
Classifier: Topic :: Adaptive Technologies
Classifier: Topic :: Scientific/Engineering
Classifier: Topic :: Scientific/Engineering :: Interface Engine/Protocol Translator
Classifier: Topic :: Software Development
Classifier: Topic :: System :: Distributed Computing
